<?xml version="1.0" encoding="utf-8"?><Section Number="0501.046" xmlns="http://StatRev.xsd"><Catchline xml:space="preserve">Home solicitation sale; duty of businesses conducting home solicitation sales.</Catchline><SectionBody><Subsection Id="1"><Text xml:space="preserve" Style="Intro">All businesses conducting home solicitation sales in this state shall:</Text><Paragraph Id="a"><Text xml:space="preserve" Style="Intro">Ensure that all employees engaged in home solicitation sales obtain the permit required in s. 501.022 and direct all such employees to comply with all provisions of said section.</Text></Paragraph><Paragraph Id="b"><Text xml:space="preserve" Style="Intro">Direct all employees engaged in home solicitation sales to leave with the buyer a “business card,” contract, or receipt, which shall include:</Text><SubParagraph Id="1"><Text xml:space="preserve" Style="Intro">The disclosure required in s. 501.031.</Text></SubParagraph><SubParagraph Id="2"><Text xml:space="preserve" Style="Intro">The name, address, and telephone number of the parent company or sponsor.</Text></SubParagraph><SubParagraph Id="3"><Text xml:space="preserve" Style="Intro">The name, address, and telephone number of the employee making the home solicitation sale.</Text></SubParagraph></Paragraph></Subsection><Subsection Id="2"><Text xml:space="preserve" Style="Intro">In the case of telephone sales solicitations, the name, address, and telephone number of the parent company or sponsor shall be clearly and conspicuously disclosed on sales materials and contracts sent to or delivered to the buyer.</Text></Subsection></SectionBody><History xml:space="preserve">s. 2, ch. 77-350; s. 3, ch. 86-144.</History></Section>