<?xml version="1.0" encoding="utf-8"?><Section Number="1006.27" xmlns="http://StatRev.xsd"><Catchline xml:space="preserve">Pooling of school buses and related purchases by district school boards; transportation services contracts.</Catchline><SectionBody><Subsection Id="1"><Text xml:space="preserve" Style="Intro">The department shall assist district school boards in securing school buses, contractual needs, equipment, and supplies at as reasonable prices as possible by providing a plan under which district school boards may voluntarily pool their bids for such purchases. The department shall prepare bid forms and specifications, obtain quotations of prices and make such information available to district school boards in order to facilitate this service. District school boards from time to time, as prescribed by State Board of Education rule, shall furnish the department with information concerning the prices paid for such items and the department shall furnish to district school boards periodic information concerning the lowest prices at which school buses, equipment, and related supplies are available based upon comparable specifications.</Text></Subsection><Subsection Id="2"><Text xml:space="preserve" Style="Intro">If a contract between any district school board and any person, business, or entity to provide the district school board with school bus service for the transportation of students in the district provides that the person, business, or entity shall own, operate, and maintain school buses for such service, the district school board may purchase the number of buses needed for the district through the department and sell them to the person, business, or entity as a part of the contract for such service.</Text></Subsection></SectionBody><History xml:space="preserve">s. 301, ch. 2002-387.</History></Section>